MANIFEST.in
README.rst
setup.py
src/ofxstatement/__init__.py
src/ofxstatement/plugins/__init__.py
src/ofxstatement/plugins/gpc.py
src/ofxstatement/plugins/maxibps.py
src/ofxstatement/plugins/tests/__init__.py
src/ofxstatement/plugins/tests/test_gpc.py
src/ofxstatement/plugins/tests/test_maxibps.py
src/ofxstatement/plugins/tests/samples/erasvet01.txt
src/ofxstatement/plugins/tests/samples/fio_2500463051_20140430_874112025.gpc
src/ofxstatement/plugins/tests/samples/fio_2500463051_20140602_.gpc
src/ofxstatement/plugins/tests/samples/fio_2500463051_20140611_.gpc
src/ofxstatement/plugins/tests/samples/maxibps.txt
src/ofxstatement_czech.egg-info/PKG-INFO
src/ofxstatement_czech.egg-info/SOURCES.txt
src/ofxstatement_czech.egg-info/dependency_links.txt
src/ofxstatement_czech.egg-info/entry_points.txt
src/ofxstatement_czech.egg-info/namespace_packages.txt
src/ofxstatement_czech.egg-info/requires.txt
src/ofxstatement_czech.egg-info/top_level.txt
src/ofxstatement_czech.egg-info/zip-safe