Metadata-Version: 1.1
Name: ofxstatement-czech
Version: 1.2.5
Summary: Czech banks plugin for ofxstatement
Home-page: https://gitlab.com/mcepl/ofxstatement-czech
Author: Matěj Cepl
Author-email: mcepl@cepl.eu
License: GPLv3
Keywords: ofx,ofxstatement
Platform: UNKNOWN
Classifier: Development Status :: 3 - Alpha
Classifier: Programming Language :: Python :: 3
Classifier: Natural Language :: English
Classifier: Topic :: Office/Business :: Financial :: Accounting
Classifier: Topic :: Utilities
Classifier: Environment :: Console
Classifier: Operating System :: OS Independent
Classifier: License :: OSI Approved :: GNU Affero General Public License v3
